LICENSE
MANIFEST.in
README.rst
requirements.txt
setup.py
django_organice_theme.egg-info/PKG-INFO
django_organice_theme.egg-info/SOURCES.txt
django_organice_theme.egg-info/dependency_links.txt
django_organice_theme.egg-info/not-zip-safe
django_organice_theme.egg-info/requires.txt
django_organice_theme.egg-info/top_level.txt
organice_theme/__init__.py
organice_theme/static/css/jquery-ui.css
organice_theme/static/css/styles.css
organice_theme/static/css/fonts/bootstrap/glyphicons-halflings-regular.eot
organice_theme/static/css/fonts/bootstrap/glyphicons-halflings-regular.svg
organice_theme/static/css/fonts/bootstrap/glyphicons-halflings-regular.ttf
organice_theme/static/css/fonts/bootstrap/glyphicons-halflings-regular.woff
organice_theme/static/js/jquery-ui.js
organice_theme/static/js/scripts.js
organice_theme/static/js/ie/html5shiv-printshiv.js
organice_theme/static/js/ie/html5shiv.js
organice_theme/static/js/ie/respond.min.js
organice_theme/static/todo/css/styles.css
organice_theme/static/todo/css/ui.datepicker.css
organice_theme/static/todo/js/jquery.tablednd_0_5.js
organice_theme/templates/400.html
organice_theme/templates/403.html
organice_theme/templates/404.html
organice_theme/templates/500.html
organice_theme/templates/base.html
organice_theme/templates/cms_base.html
organice_theme/templates/cms_bookmarks.html
organice_theme/templates/profile_dropdown.html
organice_theme/templates/skeleton.html
organice_theme/templates/account/login.html
organice_theme/templates/account/signup.html
organice_theme/templates/menu/breadcrumb.html
organice_theme/templates/menu/language_chooser.html
organice_theme/templates/newsletter/base.html
organice_theme/templates/newsletter/mailing_list_subscribe.html
organice_theme/templates/zinnia/_entry_detail_base.html
organice_theme/templates/zinnia/base.html
organice_theme/templates/zinnia/entry_archive.html
organice_theme/templates/zinnia/entry_archive_day.html
organice_theme/templates/zinnia/entry_archive_month.html
organice_theme/templates/zinnia/entry_archive_year.html
organice_theme/templates/zinnia/entry_detail_base.html
organice_theme/templates/zinnia/entry_list.html
organice_theme/templates/zinnia/tags/breadcrumbs.html
organice_theme/templates/zinnia/tags/slider_entries.html